MANIFEST.in
README.rst
setup.py
nslocalized/__init__.py
nslocalized/store.py
nslocalized/utils.py
nslocalized.egg-info/PKG-INFO
nslocalized.egg-info/SOURCES.txt
nslocalized.egg-info/dependency_links.txt
nslocalized.egg-info/requires.txt
nslocalized.egg-info/top_level.txt
tests/__init__.py
tests/test_basics.py