Metadata-Version: 1.1
Name: nslocalized
Version: 0.2.0
Summary: Reads and writes Mac OS X .strings files
Home-page: http://bitbucket.org/al45tair/nslocalized
Author: Alastair Houghton
Author-email: alastair@alastairs-place.net
License: MIT License
Platform: UNKNOWN
Classifier: Development Status :: 4 - Beta
Classifier: License :: OSI Approved :: MIT License
Classifier: Topic :: Software Development :: Internationalization
Provides: nslocalized
